{
  "dataList": [
    {
      "id": "get_10302_1",
      "desc": "Начало стендапа",
      "dlg": "Бля у меня кончились идеи что писать сюда"
    },
    {
      "id": "lobby_morning_10302_1",
      "desc": "Утречка чат!",
      "dlg": "Подобно первому поезду, разрезающему рассвет, я устремлюсь вперёд с неиссякаемым рвением!"
    },
    {
      "id": "lobby_noon_10302_1",
      "desc": "Обед уютненько",
      "dlg": "Подумать только, компания предоставляет обеды...! Я в восторге! Я бы осталась здесь работать на целую вечность, если бы могла!"
    },
    {
      "id": "lobby_night_10302_1",
      "desc": "Вечер в хату",
      "dlg": "Я приложила все усилия, чтобы записать сегодняшнее собрание! Узрите, я использовала великое множество цветов для украшения записей! Со звёздочками и цветочками и..."
    },
    {
      "id": "smalltalk_10302_1",
      "desc": "Пиздёж №1",
      "dlg": "Вы когда-нибудь ездили на поездах корпорации W, Сэр Менеджер? Ни разу?! Постойте, я... Дайте мне минутку."
    },
    {
      "id": "smalltalk_10302_2",
      "desc": "Пиздёж №2",
      "dlg": "Что думаете о том, чтобы отправиться в путешествие на поезде вместе, Сэр Менеджер? Я приготовлю нам обед!"
    },
    {
      "id": "smalltalk_10302_3",
      "desc": "Пиздёж №3",
      "dlg": "Вы не видели госпожу Родю где-нибудь? Я обещала ей провести подробную лекцию об истории корпорации W, но её  нигде нет!"
    },
    {
      "id": "smalltalk_10302_4",
      "desc": "Пиздёж после Кормления спермой №1",
      "dlg": "Сэр Менеджер, мне кажется, или в воздухе витает этот щекочущий нос металлический запах?"
    },
    {
      "id": "smalltalk_10302_5",
      "desc": "Пиздёж после Кормления спермой №2",
      "dlg": "Знаете ли вы, что человеческая жизнь куда более устойчива, чем кажется? Можно всё ещё дышать даже после сильной кровопотери и переломов большинства костей."
    },
    {
      "id": "neglect_10302_1",
      "desc": "Чесание яичек",
      "dlg": "...и вот так достижения корпорации W стали широко извест— Хм? Сэр Менеджер?"
    },
    {
      "id": "gacksung_10302_1",
      "desc": "Кормление спермой",
      "dlg": "Неужели мне наконец доверят важное задание?!"
    },
    {
      "id": "formation_10302_1",
      "desc": "Приглашение на СВО",
      "dlg": "Вперёд!"
    },
    {
      "id": "battleentry_10302_1",
      "desc": "ВЫПУСКАЙТЕ КРАКЕНА!!!",
      "dlg": "Я помчусь вперёд, словно поезд!"
    },
    {
      "id": "battle_select_10302_1",
      "desc": "Пикми",
      "dlg": "Я всегда готова мчаться вперёд!"
    },
    {
      "id": "battle_endcommand_10302_1",
      "desc": "Мощный чапалах",
      "dlg": "Никто меня не остановит!"
    },
    {
      "id": "battle_enemy_break_10302_1",
      "desc": "Удар по яйцам",
      "dlg": "Похоже, сейчас наш шанс!"
    },
    {
      "id": "battle_break_10302_1",
      "desc": "Похмельцо",
      "dlg": "Ух!"
    },
    {
      "id": "battle_kill_10302_1",
      "desc": "Славянский зажим яйцами",
      "dlg": "Куда дальше?!"
    },
    {
      "id": "battle_allydead_10302_1",
      "desc": "Угостил друга шаурмой с вокзала",
      "dlg": "Сэр Менеджер! Я рассчитываю на вас, когда всё это закончится!"
    },
    {
      "id": "choice_success_p_10302_1",
      "desc": "Успешно сданный тест на дауна",
      "dlg": "Сэр Менеджер! Я весьма впечатляюще справилась, не так ли?"
    },
    {
      "id": "choice_fail_n_10302_1",
      "desc": "Проваленный тест на дауна",
      "dlg": "Я безмерно сожалею, было крайне важно преуспеть..."
    },
    {
      "id": "battle_clear_10302_1",
      "desc": "ГОЙДАААААААААА!!!!",
      "dlg": "ВОТ это ценное приобретение для компании!"
    },
    {
      "id": "battle_clear_ex_10302_1",
      "desc": "Ультрапраймовая ГОЙДАААААААААА!!!!",
      "dlg": "Неужели я стала так называемой элитой?! Повысьте меня, Сэр Менеджер!"
    },
    {
      "id": "battle_defeat_10302_1",
      "desc": "Тима раков, я ливаю",
      "dlg": "Я... никогда не сдамся..."
    }
  ]
}