{
  "dataList": [
    {
      "id": 0,
      "content": ""
    },
    {
      "id": 1,
      "model": "검지아비",
      "place": "Коридор Указательного",
      "content": "Оу, мои извинения."
    },
    {
      "id": 2,
      "model": "LCA네임드2",
      "content": "Ааа..."
    },
    {
      "id": 3,
      "model": "검지아비",
      "content": "Я ещё не совсем привык к этой форме оружия..."
    },
    {
      "id": 4,
      "model": "검지아비",
      "content": "Так что я мог принести вам излишние страдания."
    },
    {
      "id": 5,
      "model": "LCA네임드2",
      "content": "Неи... справность...?"
    },
    {
      "id": 6,
      "model": "검지아비",
      "content": "Это не моих рук дело. У меня не было никакой причины подготавливать вам такую ловушку."
    },
    {
      "id": 7,
      "model": "검지아비",
      "content": "Вам стоило лучше позаботиться о своих оружиях, когда у вас было время. Оружия, что ломаются, когда и вправду нужны... вовсе не оружия."
    },
    {
      "id": 8,
      "model": "검지아비",
      "content": "Не стоит всё усложнять."
    },
    {
      "id": 9,
      "model": "검지아비",
      "content": "Удача просто стала на мою сторону - всего-то."
    },
    {
      "id": 10,
      "model": "검지아비",
      "content": "А..."
    },
    {
      "id": 11,
      "model": "검지아비",
      "content": "Посмотрим..."
    },
    {
      "id": 12,
      "model": "검지아비",
      "content": "Полагаю, всё что осталось - ждать?"
    }
  ]
}